HIRISEimgs-1.0.0.dist-info/DESCRIPTION.rst
HIRISEimgs-1.0.0.dist-info/METADATA
HIRISEimgs-1.0.0.dist-info/RECORD
HIRISEimgs-1.0.0.dist-info/WHEEL
HIRISEimgs-1.0.0.dist-info/metadata.json
HIRISEimgs-1.0.0.dist-info/top_level.txt
hirise/Hirise_Image.py
hirise/Image_Client.py
hirise/__init__.py
hirise/hirise_data.csv
hirise/theme_data.csv
hirise/utils.py
models/Affinity_Propagation.py
models/Agglomerative_Clustering.py
models/BIRCH.py
models/DBSCAN.py
models/Ensemble_Models.py
models/HDBSCAN.py
models/KMeans.py
models/Mean_Shift.py
models/OPTICS.py
models/__init__.py
models/metrics.py
models/utils.py
preprocessing/Data_Preparation.py
preprocessing/Dimension_Reduction.py
preprocessing/Encoding.py
preprocessing/Image_Loader.py
preprocessing/__init__.py
preprocessing/utils.py
tests/__init__.py
tests/encoded_samples.csv
tests/label_list.csv
tests/test_hirise.py
tests/test_models.py
tests/test_preprocessing.py
