Metadata-Version: 2.0
Name: HIRISEimgs
Version: 1.0.0
Summary: HIRISE Image Data, Information, Preprocessing and Models
Home-page: UNKNOWN
Author: Niranjana Sundararajan
Author-email: <niranjanasundararajan@gmail.com>
License: MIT
Keywords: python,HIRISE,NASA,PDS,API,image data
Platform: UNKNOWN
Classifier: Development Status :: 4 - Beta
Classifier: Intended Audience :: Science/Research
Classifier: License :: OSI Approved :: MIT License
Classifier: Operating System :: Unix
Classifier: Operating System :: MacOS :: MacOS X
Classifier: Operating System :: Microsoft :: Windows
Requires-Python: >3.5.2
Requires-Dist: wheel
Requires-Dist: humanize
Requires-Dist: requests
Requires-Dist: beautifulsoup4
Requires-Dist: umap-learn
Requires-Dist: hdbscan
Requires-Dist: rasterfairy
Requires-Dist: pytest
